tmcp_client/__init__.py
tmcp_client/bridge.py
tmcp_client/cli.py
tmcp_client/py.typed
tmcp_client-1.0.5.dist-info/licenses/LICENSE
tmcp_client-1.0.5.dist-info/METADATA
tmcp_client-1.0.5.dist-info/WHEEL
tmcp_client-1.0.5.dist-info/entry_points.txt
tmcp_client-1.0.5.dist-info/top_level.txt
tmcp_client-1.0.5.dist-info/RECORD
