Metadata-Version: 2.4
Name: tmcp-client
Version: 1.0.5
Summary: Lightweight MCP client for TowardsAGI MCP servers
Author-email: "TowardsAGI.AI UK Ltd" <support@towardsagi.ai>, Mansoor Pasha Iqbal <mansoor.pasha@quantumics.ai>
Maintainer-email: Mansoor Pasha Iqbal <mansoor.pasha@quantumics.ai>
License-Expression: MIT
Project-URL: Homepage, https://github.com/TowardsAGI-AI/tmcp-client
Project-URL: Documentation, https://github.com/TowardsAGI-AI/tmcp-client#readme
Project-URL: Repository, https://github.com/TowardsAGI-AI/tmcp-client.git
Project-URL: Issues, https://github.com/TowardsAGI-AI/tmcp-client/issues
Project-URL: Bug Tracker, https://github.com/TowardsAGI-AI/tmcp-client/issues
Keywords: mcp,model-context-protocol,client,towardsagi,tmcp
Classifier: Development Status :: 5 - Production/Stable
Classifier: Intended Audience :: Developers
Classifier: Operating System :: OS Independent
Classifier: Programming Language :: Python :: 3
Classifier: Programming Language :: Python :: 3.8
Classifier: Programming Language :: Python :: 3.9
Classifier: Programming Language :: Python :: 3.10
Classifier: Programming Language :: Python :: 3.11
Classifier: Programming Language :: Python :: 3.12
Classifier: Programming Language :: Python :: 3.13
Classifier: Topic :: Software Development :: Libraries :: Python Modules
Classifier: Topic :: Internet :: WWW/HTTP :: HTTP Servers
Classifier: Topic :: Database
Classifier: Topic :: Scientific/Engineering :: Artificial Intelligence
Requires-Python: >=3.8
License-File: LICENSE
Requires-Dist: httpx>=0.24.0
Requires-Dist: mcp>=1.0.0
Provides-Extra: dev
Requires-Dist: pytest>=7.0.0; extra == "dev"
Requires-Dist: pytest-asyncio>=0.21.0; extra == "dev"
Requires-Dist: black>=23.0.0; extra == "dev"
Requires-Dist: isort>=5.12.0; extra == "dev"
Requires-Dist: mypy>=1.0.0; extra == "dev"
Dynamic: license-file
